{"client":{"code":"CCF","name":"Cranswick Continental Foods","logoUrl":"https://promank13.azurewebsites.net/Proman/media/PDF/cranswick-continental-transparent.png"},"provider":{"name":"PROMAN UK","logoUrl":"https://proman-uk.com/img/logo.png"},"reportingYear":2026,"lastUpdated":"2026-05-19T15:12:45.8362413Z","schemaVersion":"1.0","weeksMeta":[{"w":1,"mon":"2025-12-29","sun":"2026-01-04","mon_short":"29 Dec","sun_short":"04 Jan","month":1},{"w":2,"mon":"2026-01-05","sun":"2026-01-11","mon_short":"05 Jan","sun_short":"11 Jan","month":1},{"w":3,"mon":"2026-01-12","sun":"2026-01-18","mon_short":"12 Jan","sun_short":"18 Jan","month":1},{"w":4,"mon":"2026-01-19","sun":"2026-01-25","mon_short":"19 Jan","sun_short":"25 Jan","month":1},{"w":5,"mon":"2026-01-26","sun":"2026-02-01","mon_short":"26 Jan","sun_short":"01 Feb","month":2},{"w":6,"mon":"2026-02-02","sun":"2026-02-08","mon_short":"02 Feb","sun_short":"08 Feb","month":2},{"w":7,"mon":"2026-02-09","sun":"2026-02-15","mon_short":"09 Feb","sun_short":"15 Feb","month":2},{"w":8,"mon":"2026-02-16","sun":"2026-02-22","mon_short":"16 Feb","sun_short":"22 Feb","month":2},{"w":9,"mon":"2026-02-23","sun":"2026-03-01","mon_short":"23 Feb","sun_short":"01 Mar","month":3},{"w":10,"mon":"2026-03-02","sun":"2026-03-08","mon_short":"02 Mar","sun_short":"08 Mar","month":3},{"w":11,"mon":"2026-03-09","sun":"2026-03-15","mon_short":"09 Mar","sun_short":"15 Mar","month":3},{"w":12,"mon":"2026-03-16","sun":"2026-03-22","mon_short":"16 Mar","sun_short":"22 Mar","month":3},{"w":13,"mon":"2026-03-23","sun":"2026-03-29","mon_short":"23 Mar","sun_short":"29 Mar","month":3},{"w":14,"mon":"2026-03-30","sun":"2026-04-05","mon_short":"30 Mar","sun_short":"05 Apr","month":4},{"w":15,"mon":"2026-04-06","sun":"2026-04-12","mon_short":"06 Apr","sun_short":"12 Apr","month":4},{"w":16,"mon":"2026-04-13","sun":"2026-04-19","mon_short":"13 Apr","sun_short":"19 Apr","month":4},{"w":17,"mon":"2026-04-20","sun":"2026-04-26","mon_short":"20 Apr","sun_short":"26 Apr","month":4},{"w":18,"mon":"2026-04-27","sun":"2026-05-03","mon_short":"27 Apr","sun_short":"03 May","month":5},{"w":19,"mon":"2026-05-04","sun":"2026-05-10","mon_short":"04 May","sun_short":"10 May","month":5},{"w":20,"mon":"2026-05-11","sun":"2026-05-17","mon_short":"11 May","sun_short":"17 May","month":5},{"w":21,"mon":"2026-05-18","sun":"2026-05-24","mon_short":"18 May","sun_short":"24 May","month":5},{"w":22,"mon":"2026-05-25","sun":"2026-05-31","mon_short":"25 May","sun_short":"31 May","month":5},{"w":23,"mon":"2026-06-01","sun":"2026-06-07","mon_short":"01 Jun","sun_short":"07 Jun","month":6},{"w":24,"mon":"2026-06-08","sun":"2026-06-14","mon_short":"08 Jun","sun_short":"14 Jun","month":6},{"w":25,"mon":"2026-06-15","sun":"2026-06-21","mon_short":"15 Jun","sun_short":"21 Jun","month":6},{"w":26,"mon":"2026-06-22","sun":"2026-06-28","mon_short":"22 Jun","sun_short":"28 Jun","month":6},{"w":27,"mon":"2026-06-29","sun":"2026-07-05","mon_short":"29 Jun","sun_short":"05 Jul","month":7},{"w":28,"mon":"2026-07-06","sun":"2026-07-12","mon_short":"06 Jul","sun_short":"12 Jul","month":7},{"w":29,"mon":"2026-07-13","sun":"2026-07-19","mon_short":"13 Jul","sun_short":"19 Jul","month":7},{"w":30,"mon":"2026-07-20","sun":"2026-07-26","mon_short":"20 Jul","sun_short":"26 Jul","month":7},{"w":31,"mon":"2026-07-27","sun":"2026-08-02","mon_short":"27 Jul","sun_short":"02 Aug","month":8},{"w":32,"mon":"2026-08-03","sun":"2026-08-09","mon_short":"03 Aug","sun_short":"09 Aug","month":8},{"w":33,"mon":"2026-08-10","sun":"2026-08-16","mon_short":"10 Aug","sun_short":"16 Aug","month":8},{"w":34,"mon":"2026-08-17","sun":"2026-08-23","mon_short":"17 Aug","sun_short":"23 Aug","month":8},{"w":35,"mon":"2026-08-24","sun":"2026-08-30","mon_short":"24 Aug","sun_short":"30 Aug","month":8},{"w":36,"mon":"2026-08-31","sun":"2026-09-06","mon_short":"31 Aug","sun_short":"06 Sep","month":9},{"w":37,"mon":"2026-09-07","sun":"2026-09-13","mon_short":"07 Sep","sun_short":"13 Sep","month":9},{"w":38,"mon":"2026-09-14","sun":"2026-09-20","mon_short":"14 Sep","sun_short":"20 Sep","month":9},{"w":39,"mon":"2026-09-21","sun":"2026-09-27","mon_short":"21 Sep","sun_short":"27 Sep","month":9},{"w":40,"mon":"2026-09-28","sun":"2026-10-04","mon_short":"28 Sep","sun_short":"04 Oct","month":10},{"w":41,"mon":"2026-10-05","sun":"2026-10-11","mon_short":"05 Oct","sun_short":"11 Oct","month":10},{"w":42,"mon":"2026-10-12","sun":"2026-10-18","mon_short":"12 Oct","sun_short":"18 Oct","month":10},{"w":43,"mon":"2026-10-19","sun":"2026-10-25","mon_short":"19 Oct","sun_short":"25 Oct","month":10},{"w":44,"mon":"2026-10-26","sun":"2026-11-01","mon_short":"26 Oct","sun_short":"01 Nov","month":11},{"w":45,"mon":"2026-11-02","sun":"2026-11-08","mon_short":"02 Nov","sun_short":"08 Nov","month":11},{"w":46,"mon":"2026-11-09","sun":"2026-11-15","mon_short":"09 Nov","sun_short":"15 Nov","month":11},{"w":47,"mon":"2026-11-16","sun":"2026-11-22","mon_short":"16 Nov","sun_short":"22 Nov","month":11},{"w":48,"mon":"2026-11-23","sun":"2026-11-29","mon_short":"23 Nov","sun_short":"29 Nov","month":11},{"w":49,"mon":"2026-11-30","sun":"2026-12-06","mon_short":"30 Nov","sun_short":"06 Dec","month":12},{"w":50,"mon":"2026-12-07","sun":"2026-12-13","mon_short":"07 Dec","sun_short":"13 Dec","month":12},{"w":51,"mon":"2026-12-14","sun":"2026-12-20","mon_short":"14 Dec","sun_short":"20 Dec","month":12},{"w":52,"mon":"2026-12-21","sun":"2026-12-27","mon_short":"21 Dec","sun_short":"27 Dec","month":12},{"w":53,"mon":"2026-12-28","sun":"2027-01-03","mon_short":"28 Dec","sun_short":"03 Jan","month":1}],"weeks":[{"@odata.etag":"","ItemInternalId":"45f216f3-a42f-473d-8396-9429f6fe00c9","week":"1","kpi_index":"0","value_num":"81","value_text":""},{"@odata.etag":"","ItemInternalId":"651a0623-a0e3-41f8-b16b-9acf017b6de3","week":"1","kpi_index":"1","value_num":"6437","value_text":""},{"@odata.etag":"","ItemInternalId":"04631950-3619-4f69-8607-e76de0375ea5","week":"1","kpi_index":"3","value_num":"51","value_text":""},{"@odata.etag":"","ItemInternalId":"17fea0e1-ab6b-421b-b8a8-e6915216f92a","week":"1","kpi_index":"4","value_num":"30","value_text":""},{"@odata.etag":"","ItemInternalId":"7a4b253a-125e-42eb-ac65-0eeef1f960f4","week":"1","kpi_index":"5","value_num":"81","value_text":""},{"@odata.etag":"","ItemInternalId":"ce62f0d1-4c08-43b3-a734-e46527d14dc1","week":"1","kpi_index":"6","value_num":"0","value_text":""},{"@odata.etag":"","ItemInternalId":"70d22647-76ae-4384-89d0-0937dcc9d1ec","week":"1","kpi_index":"7","value_num":"25","value_text":""},{"@odata.etag":"","ItemInternalId":"6a4f0f29-effa-4168-9b86-64c2a69390d2","week":"1","kpi_index":"8","value_num":"32","value_text":""},{"@odata.etag":"","ItemInternalId":"788d3754-f4ff-4724-829c-cf7a3f359400","week":"1","kpi_index":"9","value_num":"15","value_text":""},{"@odata.etag":"","ItemInternalId":"70d1c0ae-1743-4ed1-ad33-97e683dda5aa","week":"1","kpi_index":"10","value_num":"5","value_text":""},{"@odata.etag":"","ItemInternalId":"89093a13-e946-4d15-9cff-a27ca92fdbaa","week":"1","kpi_index":"11","value_num":"4","value_text":""},{"@odata.etag":"","ItemInternalId":"66ac705a-1e40-424a-81b3-9e2f7716020d","week":"1","kpi_index":"12","value_num":"1","value_text":""},{"@odata.etag":"","ItemInternalId":"d2e988a0-446f-4986-bff4-5cf65450c28f","week":"1","kpi_index":"13","value_num":"1","value_text":""},{"@odata.etag":"","ItemInternalId":"c59ff204-40bd-4a90-b2e8-a6b95b9e4547","week":"1","kpi_index":"14","value_num":"4","value_text":""},{"@odata.etag":"","ItemInternalId":"69b1b2da-4733-44a9-94ea-fe4087548e67","week":"1","kpi_index":"15","value_num":"1","value_text":""},{"@odata.etag":"","ItemInternalId":"9334ae88-175a-4423-9ae4-b935f5193586","week":"1","kpi_index":"16","value_num":"34","value_text":""},{"@odata.etag":"","ItemInternalId":"fe7c30d7-1e89-47af-ae38-28a595a46e06","week":"1","kpi_index":"17","value_num":"7","value_text":""},{"@odata.etag":"","ItemInternalId":"4863b5b9-373c-4821-be8f-8289f4070b0d","week":"1","kpi_index":"18","value_num":"24","value_text":""},{"@odata.etag":"","ItemInternalId":"abb89198-a93c-4a0a-96c4-8f375a29f8bd","week":"1","kpi_index":"19","value_num":"10","value_text":""},{"@odata.etag":"","ItemInternalId":"041b8110-8827-409c-b961-83f9cd531b5c","week":"1","kpi_index":"20","value_num":"","value_text":"Afghanistan x2, Angola x1, Dominican Republic x1, El Salvador x1, Ghanaian x1, Guinea-Bissau x1, Kenya x1, Mali x1, Somalia x1, Sudan x2, Sri Lanka x1, Saudi Arabia x1"},{"@odata.etag":"","ItemInternalId":"f6b7605c-afc1-4087-ae42-f6ffe2214055","week":"1","kpi_index":"21","value_num":"","value_text":""},{"@odata.etag":"","ItemInternalId":"2d7b893a-2cc4-4a00-b206-004afb075210","week":"1","kpi_index":"22","value_num":"0","value_text":""},{"@odata.etag":"","ItemInternalId":"d29637a5-e15e-4668-8803-10bca5953fca","week":"1","kpi_index":"23","value_num":"0","value_text":""},{"@odata.etag":"","ItemInternalId":"029c9615-bd54-4c40-be8f-b5d83f165389","week":"1","kpi_index":"24","value_num":"3","value_text":""},{"@odata.etag":"","ItemInternalId":"c03f580a-03ea-4cb6-88cf-bf40280fa352","week":"1","kpi_index":"25","value_num":"1410","value_text":""},{"@odata.etag":"","ItemInternalId":"5fe33595-a8e8-4b3a-b54c-bed77f9defe2","week":"1","kpi_index":"26","value_num":"1395","value_text":""},{"@odata.etag":"","ItemInternalId":"22ac02e0-044e-46c8-b2e4-bd3c3ab2395e","week":"1","kpi_index":"27","value_num":"1380","value_text":""},{"@odata.etag":"","ItemInternalId":"adc292aa-fb53-40d1-8a1e-ed8cead68fb3","week":"1","kpi_index":"28","value_num":"80","value_text":""},{"@odata.etag":"","ItemInternalId":"54c95629-d26d-4f36-9a1d-06fe35b2f16d","week":"1","kpi_index":"29","value_num":"","value_text":""},{"@odata.etag":"","ItemInternalId":"c32915ad-a8a1-45af-b87b-636ffcb8196c","week":"2","kpi_index":"0","value_num":"85","value_text":""},{"@odata.etag":"","ItemInternalId":"668f7a81-2a25-43de-af10-a97977b22c85","week":"2","kpi_index":"1","value_num":"6817","value_text":""},{"@odata.etag":"","ItemInternalId":"d6185bc7-a047-48ec-bcfd-e100bf18b14e","week":"2","kpi_index":"3","value_num":"51","value_text":""},{"@odata.etag":"","ItemInternalId":"81a09578-5e1c-49b5-81d8-ad0f1529bd0c","week":"2","kpi_index":"4","value_num":"34","value_text":""},{"@odata.etag":"","ItemInternalId":"90e4ea5a-91ef-45a2-a14a-60d26be3ebc2","week":"2","kpi_index":"5","value_num":"85","value_text":""},{"@odata.etag":"","ItemInternalId":"dbdec53a-9030-48d9-b6a2-d05e8903a748","week":"2","kpi_index":"6","value_num":"0","value_text":""},{"@odata.etag":"","ItemInternalId":"8f105b97-037f-4a03-b978-7660ebe00b08","week":"2","kpi_index":"7","value_num":"28","value_text":""},{"@odata.etag":"","ItemInternalId":"6252ab44-916f-4be6-afb8-2ee8cd6725ba","week":"2","kpi_index":"8","value_num":"32","value_text":""},{"@odata.etag":"","ItemInternalId":"d5012b78-496d-4c4d-96d9-22497dd02916","week":"2","kpi_index":"9","value_num":"16","value_text":""},{"@odata.etag":"","ItemInternalId":"a5c37c2e-2eb2-4044-91ee-fcc3605c6e9d","week":"2","kpi_index":"10","value_num":"5","value_text":""},{"@odata.etag":"","ItemInternalId":"8bf51218-959f-4d74-8114-ff43222958d5","week":"2","kpi_index":"11","value_num":"4","value_text":""},{"@odata.etag":"","ItemInternalId":"afdd0629-cebf-48e5-8590-f9d9888396c6","week":"2","kpi_index":"12","value_num":"1","value_text":""},{"@odata.etag":"","ItemInternalId":"195a68a4-d1a8-47e1-bd4e-cdd8359591bb","week":"2","kpi_index":"13","value_num":"1","value_text":""},{"@odata.etag":"","ItemInternalId":"b61d43c6-7d29-409a-b842-ffb08cdea5f9","week":"2","kpi_index":"14","value_num":"4","value_text":""},{"@odata.etag":"","ItemInternalId":"ac9e7b34-aa89-479c-bf5a-ea500506f8ce","week":"2","kpi_index":"15","value_num":"1","value_text":""},{"@odata.etag":"","ItemInternalId":"f6ad3224-87bc-4257-894e-03cbecebe3e8","week":"2","kpi_index":"16","value_num":"35","value_text":""},{"@odata.etag":"","ItemInternalId":"b0529722-c3cd-4c16-b8af-c75558f5b412","week":"2","kpi_index":"17","value_num":"8","value_text":""},{"@odata.etag":"","ItemInternalId":"dd91ab31-876f-4121-9d95-9b0b7de17e51","week":"2","kpi_index":"18","value_num":"25","value_text":""},{"@odata.etag":"","ItemInternalId":"c447f49b-7cef-475f-a2f0-e031c92f4ddb","week":"2","kpi_index":"19","value_num":"10","value_text":""},{"@odata.etag":"","ItemInternalId":"b92dd9c0-0022-453a-a9f2-d352006cc734","week":"2","kpi_index":"20","value_num":"","value_text":"Afghanistan x2, Angola x1, Dominican Republic x1, El Salvador x1, Ghanaian x1, Guinea-Bissau x1, Kenya x1, Mali x1, Somalia x1, Sudan x2, Sri Lanka x1, Saudi Arabia x1"},{"@odata.etag":"","ItemInternalId":"09985396-dd21-4a2f-8b34-ce0caa3c1e19","week":"2","kpi_index":"21","value_num":"","value_text":""},{"@odata.etag":"","ItemInternalId":"958e2e30-7580-4700-977f-ac98d4a8b112","week":"2","kpi_index":"22","value_num":"0","value_text":""},{"@odata.etag":"","ItemInternalId":"b3b93900-6b44-4e87-8a37-a2339ef06efc","week":"2","kpi_index":"23","value_num":"0","value_text":""},{"@odata.etag":"","ItemInternalId":"f3407489-b781-485f-ad47-cdece0d8b7f5","week":"2","kpi_index":"24","value_num":"4","value_text":""},{"@odata.etag":"","ItemInternalId":"ac6ab33a-afc3-47b0-afcf-05f132a6bc86","week":"2","kpi_index":"25","value_num":"1450","value_text":""},{"@odata.etag":"","ItemInternalId":"5a72cf70-4541-4ae4-8571-895139d4c00b","week":"2","kpi_index":"26","value_num":"1445","value_text":""},{"@odata.etag":"","ItemInternalId":"0ecf223c-ee96-4e10-b1ed-f3c29cf02a39","week":"2","kpi_index":"27","value_num":"1440","value_text":""},{"@odata.etag":"","ItemInternalId":"45471ece-8788-4959-9b05-08b0eea64941","week":"2","kpi_index":"28","value_num":"83","value_text":""},{"@odata.etag":"","ItemInternalId":"62c64f16-2140-4ffd-9bf4-d8b08a7714c1","week":"2","kpi_index":"29","value_num":"","value_text":""},{"@odata.etag":"","ItemInternalId":"4b04abd8-aea2-4ac0-b70b-4f6351d02540","week":"3","kpi_index":"0","value_num":"88","value_text":""},{"@odata.etag":"","ItemInternalId":"930fe03f-aea5-463c-923f-0da5fbaf3da4","week":"3","kpi_index":"1","value_num":"7022.4","value_text":""},{"@odata.etag":"","ItemInternalId":"1db1a530-bdc3-4f44-ab9f-bb98b472bd30","week":"3","kpi_index":"3","value_num":"53","value_text":""},{"@odata.etag":"","ItemInternalId":"fdc5be96-a875-4997-9c61-8f4f43a3e6ec","week":"3","kpi_index":"4","value_num":"35","value_text":""},{"@odata.etag":"","ItemInternalId":"a471cfa4-913b-48ac-a7cf-f4194bba7a57","week":"3","kpi_index":"5","value_num":"88","value_text":""},{"@odata.etag":"","ItemInternalId":"f3dbf6a6-85f2-414b-ac1d-752d8709ef87","week":"3","kpi_index":"6","value_num":"0","value_text":""},{"@odata.etag":"","ItemInternalId":"cd20743d-cc3e-4dad-8768-843eafb1bbab","week":"3","kpi_index":"7","value_num":"29","value_text":""},{"@odata.etag":"","ItemInternalId":"d31a357d-f31c-48a5-a4ef-243532498d15","week":"3","kpi_index":"8","value_num":"33","value_text":""},{"@odata.etag":"","ItemInternalId":"5eaf4d1d-0915-4750-a372-fca013f249f5","week":"3","kpi_index":"9","value_num":"17","value_text":""},{"@odata.etag":"","ItemInternalId":"3f6bc9c0-4ea4-4754-835a-8ca6daaec406","week":"3","kpi_index":"10","value_num":"5","value_text":""},{"@odata.etag":"","ItemInternalId":"5aca9d5a-ad49-470d-ae54-9fb555117075","week":"3","kpi_index":"11","value_num":"4","value_text":""},{"@odata.etag":"","ItemInternalId":"5df694c2-43d1-49cc-9ba4-b7fa1882c6a5","week":"3","kpi_index":"12","value_num":"1","value_text":""},{"@odata.etag":"","ItemInternalId":"8a8f9834-520c-465f-ab14-d42ae9ac5608","week":"3","kpi_index":"13","value_num":"1","value_text":""},{"@odata.etag":"","ItemInternalId":"fa8d5e82-98db-45df-9c9b-90502ae8a475","week":"3","kpi_index":"14","value_num":"4","value_text":""},{"@odata.etag":"","ItemInternalId":"f1cd4c1f-54c8-4b9a-ac0b-0d04c58b3fc8","week":"3","kpi_index":"15","value_num":"1","value_text":""},{"@odata.etag":"","ItemInternalId":"3fdcfac2-bffd-4784-9589-4f83fade5d38","week":"3","kpi_index":"16","value_num":"37","value_text":""},{"@odata.etag":"","ItemInternalId":"c8706405-6b33-4c26-9fc6-45bc98e12d5a","week":"3","kpi_index":"17","value_num":"8","value_text":""},{"@odata.etag":"","ItemInternalId":"61bb494a-886f-48a9-84f4-be58a2e24b2c","week":"3","kpi_index":"18","value_num":"26","value_text":""},{"@odata.etag":"","ItemInternalId":"5b56fb98-a1ba-4fc3-beaa-a19241a93838","week":"3","kpi_index":"19","value_num":"10","value_text":""},{"@odata.etag":"","ItemInternalId":"0627fda8-379c-4973-acc9-2a48846a98bc","week":"3","kpi_index":"20","value_num":"","value_text":"Afghanistan x2, Angola x1, Dominican Republic x1, El Salvador x1, Ghanaian x1, Guinea-Bissau x1, Kenya x1, Mali x1, Somalia x1, Sudan x2, Sri Lanka x1, Saudi Arabia x1"},{"@odata.etag":"","ItemInternalId":"981457ea-531d-4dfa-9961-f8c5f97238fb","week":"3","kpi_index":"21","value_num":"","value_text":""},{"@odata.etag":"","ItemInternalId":"885f2d2c-14bc-42a8-a84d-75d2d34dd134","week":"3","kpi_index":"22","value_num":"0","value_text":""},{"@odata.etag":"","ItemInternalId":"f8faf82c-08b0-4356-8bf9-606d89704725","week":"3","kpi_index":"23","value_num":"1","value_text":""},{"@odata.etag":"","ItemInternalId":"96cd1559-eeef-4abf-a008-591d13a4e471","week":"3","kpi_index":"24","value_num":"2","value_text":""},{"@odata.etag":"","ItemInternalId":"944a00b5-8bba-449f-be3b-926bbf180fc0","week":"3","kpi_index":"25","value_num":"1500","value_text":""},{"@odata.etag":"","ItemInternalId":"2994447b-a8c4-4789-868b-2401ebe56083","week":"3","kpi_index":"26","value_num":"1490","value_text":""},{"@odata.etag":"","ItemInternalId":"ce7655b8-053f-4fc0-8cc1-c2aed6d9c643","week":"3","kpi_index":"27","value_num":"1475","value_text":""},{"@odata.etag":"","ItemInternalId":"467f8992-04bb-4458-b8f8-7b5be74f83b0","week":"3","kpi_index":"28","value_num":"85","value_text":""},{"@odata.etag":"","ItemInternalId":"fc7d4064-bf8f-4680-ae9b-745b6f55346f","week":"3","kpi_index":"29","value_num":"","value_text":"Minor slip in chilled area, no injury. Reviewed with site H&S team."},{"@odata.etag":"","ItemInternalId":"35506672-cff2-486e-b585-9bf8c1a522ec","week":"4","kpi_index":"0","value_num":"90","value_text":""},{"@odata.etag":"","ItemInternalId":"2524f0c4-ee50-4122-a860-13add97135e2","week":"4","kpi_index":"1","value_num":"7245","value_text":""},{"@odata.etag":"","ItemInternalId":"77b39249-682d-4d87-bae3-a3a078a5b76f","week":"4","kpi_index":"3","value_num":"54","value_text":""},{"@odata.etag":"","ItemInternalId":"549b5753-61a2-4927-9278-c3c62cf1c5f8","week":"4","kpi_index":"4","value_num":"36","value_text":""},{"@odata.etag":"","ItemInternalId":"2a53718e-5ade-4d8c-a7fb-db563ccf4959","week":"4","kpi_index":"5","value_num":"90","value_text":""},{"@odata.etag":"","ItemInternalId":"cf83cb7d-2d6d-4a1e-92db-77af333736ac","week":"4","kpi_index":"6","value_num":"0","value_text":""},{"@odata.etag":"","ItemInternalId":"e27c0d1a-df91-4d10-9bcb-4a4fc8343d7e","week":"4","kpi_index":"7","value_num":"29","value_text":""},{"@odata.etag":"","ItemInternalId":"712f9d88-55ab-4987-a08b-49242d418784","week":"4","kpi_index":"8","value_num":"34","value_text":""},{"@odata.etag":"","ItemInternalId":"d6eeb8fb-b9f9-452b-aeee-166f6476c756","week":"4","kpi_index":"9","value_num":"17","value_text":""},{"@odata.etag":"","ItemInternalId":"85daccc3-68c2-495f-8b63-c8220061d43f","week":"4","kpi_index":"10","value_num":"5","value_text":""},{"@odata.etag":"","ItemInternalId":"9970a1b5-c076-4231-a7ee-83ec2a3d05f7","week":"4","kpi_index":"11","value_num":"5","value_text":""},{"@odata.etag":"","ItemInternalId":"78fc01e2-053a-4a60-8283-02f7ee564353","week":"4","kpi_index":"12","value_num":"1","value_text":""},{"@odata.etag":"","ItemInternalId":"7b127b08-7ee0-4ae2-84c9-515dcc78034d","week":"4","kpi_index":"13","value_num":"1","value_text":""},{"@odata.etag":"","ItemInternalId":"bf8382e7-5d2a-4859-92d8-c8b7a269eed8","week":"4","kpi_index":"14","value_num":"4","value_text":""},{"@odata.etag":"","ItemInternalId":"96a0cbea-d809-44ba-8cd7-827c2568f2d8","week":"4","kpi_index":"15","value_num":"1","value_text":""},{"@odata.etag":"","ItemInternalId":"20ca4aee-7c8e-48dd-80ff-ce40e2b1f303","week":"4","kpi_index":"16","value_num":"37","value_text":""},{"@odata.etag":"","ItemInternalId":"cd3fc238-4add-4d2a-85f3-96c83ca5b632","week":"4","kpi_index":"17","value_num":"8","value_text":""},{"@odata.etag":"","ItemInternalId":"fd3a39fc-8317-4acb-8601-9d74822dbed0","week":"4","kpi_index":"18","value_num":"27","value_text":""},{"@odata.etag":"","ItemInternalId":"7a3f9165-dd8d-451e-b4a4-e9d81f13f603","week":"4","kpi_index":"19","value_num":"11","value_text":""},{"@odata.etag":"","ItemInternalId":"a5d1e2fd-cbfb-4b91-9f1f-a032fb111103","week":"4","kpi_index":"20","value_num":"","value_text":"Afghanistan x2, Angola x1, Dominican Republic x1, El Salvador x1, Ghanaian x1, Guinea-Bissau x1, Kenya x1, Mali x1, Somalia x1, Sudan x2, Sri Lanka x1, Saudi Arabia x1"},{"@odata.etag":"","ItemInternalId":"dd7d67cb-cace-4004-bfb3-51d553ec6253","week":"4","kpi_index":"21","value_num":"","value_text":""},{"@odata.etag":"","ItemInternalId":"137a4d73-c860-489e-82ad-f25713727817","week":"4","kpi_index":"22","value_num":"0","value_text":""},{"@odata.etag":"","ItemInternalId":"7f5c97e9-59e3-4e66-ae12-ec2ff8488767","week":"4","kpi_index":"23","value_num":"0","value_text":""},{"@odata.etag":"","ItemInternalId":"af0e00f9-4cae-46bd-b531-98daa228a38b","week":"4","kpi_index":"24","value_num":"5","value_text":""},{"@odata.etag":"","ItemInternalId":"dbb90a58-5f34-4818-9a09-21f1232c9bbe","week":"4","kpi_index":"25","value_num":"1530","value_text":""},{"@odata.etag":"","ItemInternalId":"45494826-3b42-4fb9-bff8-d2e288876de1","week":"4","kpi_index":"26","value_num":"1520","value_text":""},{"@odata.etag":"","ItemInternalId":"2cd6d002-a537-4518-a6b9-70db6736f78a","week":"4","kpi_index":"27","value_num":"1510","value_text":""},{"@odata.etag":"","ItemInternalId":"0a48f5a1-e12c-41ed-a331-fa36b68241f7","week":"4","kpi_index":"28","value_num":"87","value_text":""},{"@odata.etag":"","ItemInternalId":"289bd0cf-3378-41ed-9778-c546803d0409","week":"4","kpi_index":"29","value_num":"","value_text":""},{"@odata.etag":"","ItemInternalId":"75d291fb-6e9a-464e-a1e7-b9fb95feb744","week":"5","kpi_index":"0","value_num":"92","value_text":""},{"@odata.etag":"","ItemInternalId":"1d1d5d4b-a774-4c1a-9c1a-1501387a90c8","week":"5","kpi_index":"1","value_num":"7452","value_text":""},{"@odata.etag":"","ItemInternalId":"551ac026-75a3-4c00-b257-a96c0a26cfb2","week":"5","kpi_index":"3","value_num":"56","value_text":""},{"@odata.etag":"","ItemInternalId":"efa8f2e7-72f7-4f32-b2b4-bdf7178d43e2","week":"5","kpi_index":"4","value_num":"36","value_text":""},{"@odata.etag":"","ItemInternalId":"21e9e04a-b701-4cb8-b536-0347175a1588","week":"5","kpi_index":"5","value_num":"92","value_text":""},{"@odata.etag":"","ItemInternalId":"6ec64152-6c4a-46a4-bd57-1a809e36ad73","week":"5","kpi_index":"6","value_num":"0","value_text":""},{"@odata.etag":"","ItemInternalId":"8a65870d-0ceb-4b3b-83cb-045426e09bb1","week":"5","kpi_index":"7","value_num":"30","value_text":""},{"@odata.etag":"","ItemInternalId":"d1aa159f-4a2c-4228-8a49-968b20a7b382","week":"5","kpi_index":"8","value_num":"35","value_text":""},{"@odata.etag":"","ItemInternalId":"fd2287dc-0520-45b7-8abb-8c8991bd5fd5","week":"5","kpi_index":"9","value_num":"17","value_text":""},{"@odata.etag":"","ItemInternalId":"29f112de-6218-47a8-ac23-3c9bc0f49de9","week":"5","kpi_index":"10","value_num":"5","value_text":""},{"@odata.etag":"","ItemInternalId":"e45fea8c-dc4c-4967-8624-e513a93c8bfa","week":"5","kpi_index":"11","value_num":"5","value_text":""},{"@odata.etag":"","ItemInternalId":"d1025172-502f-4728-82d5-2f68cbc6fad6","week":"5","kpi_index":"12","value_num":"1","value_text":""},{"@odata.etag":"","ItemInternalId":"8bda1f0d-af64-4143-b672-9b336e8ed04a","week":"5","kpi_index":"13","value_num":"1","value_text":""},{"@odata.etag":"","ItemInternalId":"206d2a84-1b30-48ae-b8f1-498e11e3cd8e","week":"5","kpi_index":"14","value_num":"5","value_text":""},{"@odata.etag":"","ItemInternalId":"7bf30d13-bda5-46b0-8b11-667d21c0b637","week":"5","kpi_index":"15","value_num":"1","value_text":""},{"@odata.etag":"","ItemInternalId":"4f795f1e-55e1-4932-91ba-648fc5999f6b","week":"5","kpi_index":"16","value_num":"38","value_text":""},{"@odata.etag":"","ItemInternalId":"3777b3b4-8eee-41db-b7eb-c0b9507fe17c","week":"5","kpi_index":"17","value_num":"8","value_text":""},{"@odata.etag":"","ItemInternalId":"19cedde8-8fc0-434a-9ea7-4815c59c2003","week":"5","kpi_index":"18","value_num":"27","value_text":""},{"@odata.etag":"","ItemInternalId":"7dfe0044-8273-4b3f-8e62-5d5e97cce641","week":"5","kpi_index":"19","value_num":"11","value_text":""},{"@odata.etag":"","ItemInternalId":"b04cc1a7-b67a-44ab-846a-433aa1832c61","week":"5","kpi_index":"20","value_num":"","value_text":"Afghanistan x2, Angola x1, Dominican Republic x1, El Salvador x1, Ghanaian x1, Guinea-Bissau x1, Kenya x1, Mali x1, Somalia x1, Sudan x2, Sri Lanka x1, Saudi Arabia x1"},{"@odata.etag":"","ItemInternalId":"2812e952-08bd-49b9-a878-9384d20b3ccc","week":"5","kpi_index":"21","value_num":"","value_text":""},{"@odata.etag":"","ItemInternalId":"b1a4ab31-b30f-4af2-9b0e-69837ba33b87","week":"5","kpi_index":"22","value_num":"0","value_text":""},{"@odata.etag":"","ItemInternalId":"5623efa2-ca55-45e6-bac4-3274d9fcb4ca","week":"5","kpi_index":"23","value_num":"0","value_text":""},{"@odata.etag":"","ItemInternalId":"c2e7e2fc-fc26-4f95-ad05-3ad166b79e58","week":"5","kpi_index":"24","value_num":"3","value_text":""},{"@odata.etag":"","ItemInternalId":"3c2aad63-ea6f-4cf3-b649-5173bdf70d8e","week":"5","kpi_index":"25","value_num":"1560","value_text":""},{"@odata.etag":"","ItemInternalId":"e31fae0a-c417-4dcf-9858-0eba3973dfae","week":"5","kpi_index":"26","value_num":"1550","value_text":""},{"@odata.etag":"","ItemInternalId":"af6748e7-9b5b-4b71-9569-b6217160bd9e","week":"5","kpi_index":"27","value_num":"1545","value_text":""},{"@odata.etag":"","ItemInternalId":"3c017e16-1dc6-4acb-8b4f-3e83fb4d6d5f","week":"5","kpi_index":"28","value_num":"90","value_text":""},{"@odata.etag":"","ItemInternalId":"30ea40aa-ba13-4d02-8bd9-fdc57e37ee51","week":"5","kpi_index":"29","value_num":"","value_text":""},{"@odata.etag":"","ItemInternalId":"b1cbfd23-b897-418d-9b9e-1e14345361e5","week":"6","kpi_index":"0","value_num":"94","value_text":""},{"@odata.etag":"","ItemInternalId":"9f98e56e-657c-429a-8f76-00ab2beaa39f","week":"6","kpi_index":"1","value_num":"7632.8","value_text":""},{"@odata.etag":"","ItemInternalId":"b8c7ee1a-5151-40c6-b05e-bac0fead93b2","week":"6","kpi_index":"3","value_num":"57","value_text":""},{"@odata.etag":"","ItemInternalId":"1d4f8234-d9f3-4ecf-b112-ddf8295a5871","week":"6","kpi_index":"4","value_num":"37","value_text":""},{"@odata.etag":"","ItemInternalId":"4509fe0c-a913-4d3e-b97b-670f9b782d34","week":"6","kpi_index":"5","value_num":"94","value_text":""},{"@odata.etag":"","ItemInternalId":"da267420-94e0-4d45-8317-4bd8832ed5a9","week":"6","kpi_index":"6","value_num":"0","value_text":""},{"@odata.etag":"","ItemInternalId":"d7a30f00-2346-4695-a0d1-eed263cc7a0b","week":"6","kpi_index":"7","value_num":"31","value_text":""},{"@odata.etag":"","ItemInternalId":"89190551-1dd1-4b36-958a-aa44080e1470","week":"6","kpi_index":"8","value_num":"35","value_text":""},{"@odata.etag":"","ItemInternalId":"f92f86e3-93af-4a6b-81e9-ea267883291f","week":"6","kpi_index":"9","value_num":"18","value_text":""},{"@odata.etag":"","ItemInternalId":"0ab218e9-8b2f-4bdf-b354-bc7726a3447f","week":"6","kpi_index":"10","value_num":"6","value_text":""},{"@odata.etag":"","ItemInternalId":"d456a549-23be-48bc-a978-9be3902eb9ef","week":"6","kpi_index":"11","value_num":"4","value_text":""},{"@odata.etag":"","ItemInternalId":"b5872687-438f-4bea-9899-0fd4d676eaea","week":"6","kpi_index":"12","value_num":"1","value_text":""},{"@odata.etag":"","ItemInternalId":"5c24db70-18bf-48cd-b909-b46328a08259","week":"6","kpi_index":"13","value_num":"1","value_text":""},{"@odata.etag":"","ItemInternalId":"7915ea1c-4502-49b5-8441-91faec14655c","week":"6","kpi_index":"14","value_num":"5","value_text":""},{"@odata.etag":"","ItemInternalId":"2a1b9f05-2d1f-4899-a79f-5a2e356b94db","week":"6","kpi_index":"15","value_num":"1","value_text":""},{"@odata.etag":"","ItemInternalId":"6ad428bf-779e-4d5e-80da-cf6536c8cdff","week":"6","kpi_index":"16","value_num":"39","value_text":""},{"@odata.etag":"","ItemInternalId":"915fb01b-8414-422e-a48d-88b031840648","week":"6","kpi_index":"17","value_num":"8","value_text":""},{"@odata.etag":"","ItemInternalId":"f025d3d0-c861-435d-970b-8b29c134b265","week":"6","kpi_index":"18","value_num":"28","value_text":""},{"@odata.etag":"","ItemInternalId":"a085888d-1bd2-4d74-ad14-d482567c297c","week":"6","kpi_index":"19","value_num":"11","value_text":""},{"@odata.etag":"","ItemInternalId":"b88e26d2-e633-4b84-80e0-303229e17c86","week":"6","kpi_index":"20","value_num":"","value_text":"Afghanistan x2, Angola x1, Dominican Republic x1, El Salvador x1, Ghanaian x1, Guinea-Bissau x1, Kenya x1, Mali x1, Somalia x1, Sudan x2, Sri Lanka x1, Saudi Arabia x1"},{"@odata.etag":"","ItemInternalId":"9a7f8b31-009d-4070-bf60-437cf84fc763","week":"6","kpi_index":"21","value_num":"","value_text":""},{"@odata.etag":"","ItemInternalId":"3c5d706f-958a-4303-878b-f898bcd2d142","week":"6","kpi_index":"22","value_num":"0","value_text":""},{"@odata.etag":"","ItemInternalId":"6e8e447a-d512-4efe-8d93-ccdb1c3913a5","week":"6","kpi_index":"23","value_num":"0","value_text":""},{"@odata.etag":"","ItemInternalId":"53ec2283-2c8e-4f46-8e3e-beff6cfb1a52","week":"6","kpi_index":"24","value_num":"4","value_text":""},{"@odata.etag":"","ItemInternalId":"b018bbe6-c588-4ad4-a3ef-07d1ead28d89","week":"6","kpi_index":"25","value_num":"1590","value_text":""},{"@odata.etag":"","ItemInternalId":"da31bdb5-185d-483c-85e2-3e20d22c09d5","week":"6","kpi_index":"26","value_num":"1580","value_text":""},{"@odata.etag":"","ItemInternalId":"13f3f8fd-5f86-455e-aa26-448abcf2ad4d","week":"6","kpi_index":"27","value_num":"1575","value_text":""},{"@odata.etag":"","ItemInternalId":"213d6b0e-9a6a-4b09-9b0a-974749ef94d7","week":"6","kpi_index":"28","value_num":"91","value_text":""},{"@odata.etag":"","ItemInternalId":"f1dca452-f3e2-4c83-8c53-5586c58b70c6","week":"6","kpi_index":"29","value_num":"","value_text":""},{"@odata.etag":"","ItemInternalId":"bcbbc652-7c02-49d3-a6dc-6c4465c3cb1f","week":"7","kpi_index":"0","value_num":"95","value_text":""},{"@odata.etag":"","ItemInternalId":"a83f1ec9-e25c-4f90-864e-515b5d14d212","week":"7","kpi_index":"1","value_num":"7695","value_text":""},{"@odata.etag":"","ItemInternalId":"10c1060e-6312-4141-927c-5ce3c6e3cc3f","week":"7","kpi_index":"3","value_num":"57","value_text":""},{"@odata.etag":"","ItemInternalId":"c9dd0893-f698-4efe-9f90-bba081c59d33","week":"7","kpi_index":"4","value_num":"38","value_text":""},{"@odata.etag":"","ItemInternalId":"0202cdde-344b-48c2-a6a0-10c4a1aa34c3","week":"7","kpi_index":"5","value_num":"95","value_text":""},{"@odata.etag":"","ItemInternalId":"519ef187-15e4-405b-9331-58fc40523d3c","week":"7","kpi_index":"6","value_num":"0","value_text":""},{"@odata.etag":"","ItemInternalId":"e7391879-987f-49a9-a3b3-272757877227","week":"7","kpi_index":"7","value_num":"31","value_text":""},{"@odata.etag":"","ItemInternalId":"bd974c75-2c31-4397-abf3-1eac01515c81","week":"7","kpi_index":"8","value_num":"36","value_text":""},{"@odata.etag":"","ItemInternalId":"452fb2e1-057c-4a84-bfed-a206c30c77ce","week":"7","kpi_index":"9","value_num":"18","value_text":""},{"@odata.etag":"","ItemInternalId":"5f83f657-bd41-4ca0-af95-ce9d2c54e055","week":"7","kpi_index":"10","value_num":"6","value_text":""},{"@odata.etag":"","ItemInternalId":"6ab1230f-c51e-4f46-a6b1-64032bf923d3","week":"7","kpi_index":"11","value_num":"4","value_text":""},{"@odata.etag":"","ItemInternalId":"a2112cf0-0d6e-45f8-9e99-470ac8cfba66","week":"7","kpi_index":"12","value_num":"1","value_text":""},{"@odata.etag":"","ItemInternalId":"f965497e-7d55-411e-bc31-08f6f60ac5d2","week":"7","kpi_index":"13","value_num":"1","value_text":""},{"@odata.etag":"","ItemInternalId":"9d0f5952-f6a9-411d-9272-258ef50c44da","week":"7","kpi_index":"14","value_num":"5","value_text":""},{"@odata.etag":"","ItemInternalId":"9b2b1ea2-62c8-4578-9eb3-4922419fd7d9","week":"7","kpi_index":"15","value_num":"1","value_text":""},{"@odata.etag":"","ItemInternalId":"9df97086-0a35-4a8c-8f85-5de46d7a5042","week":"7","kpi_index":"16","value_num":"40","value_text":""},{"@odata.etag":"","ItemInternalId":"0688d798-5609-44e1-88d1-fa690a863874","week":"7","kpi_index":"17","value_num":"8","value_text":""},{"@odata.etag":"","ItemInternalId":"9a37c6d3-8ebb-4dae-9cf7-ca68c02cfdf7","week":"7","kpi_index":"18","value_num":"28","value_text":""},{"@odata.etag":"","ItemInternalId":"3f8502f2-9426-458d-b357-3a644916f91b","week":"7","kpi_index":"19","value_num":"11","value_text":""},{"@odata.etag":"","ItemInternalId":"fce4f0a7-279e-4c76-a4da-de040dae6b59","week":"7","kpi_index":"20","value_num":"","value_text":"Afghanistan x2, Angola x1, Dominican Republic x1, El Salvador x1, Ghanaian x1, Guinea-Bissau x1, Kenya x1, Mali x1, Somalia x1, Sudan x2, Sri Lanka x1, Saudi Arabia x1"},{"@odata.etag":"","ItemInternalId":"2689276c-5a82-4203-8f9a-2f153f11feb7","week":"7","kpi_index":"21","value_num":"","value_text":""},{"@odata.etag":"","ItemInternalId":"c0ee7c16-c6be-47b9-8b4e-06dd07a486e4","week":"7","kpi_index":"22","value_num":"0","value_text":""},{"@odata.etag":"","ItemInternalId":"21842cef-0c9a-46d8-9dce-1ba4e9bc906d","week":"7","kpi_index":"23","value_num":"0","value_text":""},{"@odata.etag":"","ItemInternalId":"24282290-87c1-4ac9-b0bf-cb8b06c90eb2","week":"7","kpi_index":"24","value_num":"6","value_text":""},{"@odata.etag":"","ItemInternalId":"1824f0fb-465f-4b65-9dea-d4fef0866160","week":"7","kpi_index":"25","value_num":"1610","value_text":""},{"@odata.etag":"","ItemInternalId":"c02d132b-d3b6-46bf-9b19-1fa6a43b5f2b","week":"7","kpi_index":"26","value_num":"1605","value_text":""},{"@odata.etag":"","ItemInternalId":"5adea298-4b44-4e95-83c8-4fe5cc7f7a59","week":"7","kpi_index":"27","value_num":"1600","value_text":""},{"@odata.etag":"","ItemInternalId":"a9910d95-fdcf-4527-9c5e-2beb69da36e7","week":"7","kpi_index":"28","value_num":"92","value_text":""},{"@odata.etag":"","ItemInternalId":"e1a63446-e3e0-488a-a6dd-2cd390a78bfe","week":"7","kpi_index":"29","value_num":"","value_text":""},{"@odata.etag":"","ItemInternalId":"575ad382-1df9-43e8-a585-7b59dbb8d061","week":"8","kpi_index":"0","value_num":"95","value_text":""},{"@odata.etag":"","ItemInternalId":"b34598ff-200c-4adc-83d6-abf57ccd7881","week":"8","kpi_index":"1","value_num":"7676","value_text":""},{"@odata.etag":"","ItemInternalId":"8f3c9a98-2549-4027-b46a-243547807766","week":"8","kpi_index":"3","value_num":"57","value_text":""},{"@odata.etag":"","ItemInternalId":"bc23003f-323b-48f9-9572-0d64167d9ad4","week":"8","kpi_index":"4","value_num":"38","value_text":""},{"@odata.etag":"","ItemInternalId":"8b77fff2-e20f-4644-8e7e-768f7e514dbe","week":"8","kpi_index":"5","value_num":"95","value_text":""},{"@odata.etag":"","ItemInternalId":"b8850383-2268-4342-b479-847e29120472","week":"8","kpi_index":"6","value_num":"0","value_text":""},{"@odata.etag":"","ItemInternalId":"dee6c04d-9f78-458a-b197-bc51571713ea","week":"8","kpi_index":"7","value_num":"31","value_text":""},{"@odata.etag":"","ItemInternalId":"9e73e4a7-e7ec-464b-9140-b7324e7f6c3a","week":"8","kpi_index":"8","value_num":"36","value_text":""},{"@odata.etag":"","ItemInternalId":"5e55b1ce-090e-424a-8ae5-af4e94226ebb","week":"8","kpi_index":"9","value_num":"18","value_text":""},{"@odata.etag":"","ItemInternalId":"8ad140c4-d8d2-45d2-b5d5-97eeed3fd63c","week":"8","kpi_index":"10","value_num":"6","value_text":""},{"@odata.etag":"","ItemInternalId":"43446756-118a-4d3b-b86f-1487101cafab","week":"8","kpi_index":"11","value_num":"4","value_text":""},{"@odata.etag":"","ItemInternalId":"a33c3a22-2af8-4349-bf02-083bcb323488","week":"8","kpi_index":"12","value_num":"1","value_text":""},{"@odata.etag":"","ItemInternalId":"ec050639-5aa3-412d-b6e5-cfdc91088263","week":"8","kpi_index":"13","value_num":"1","value_text":""},{"@odata.etag":"","ItemInternalId":"14e7cc1e-d2ca-4b01-b145-b162e1a214ec","week":"8","kpi_index":"14","value_num":"5","value_text":""},{"@odata.etag":"","ItemInternalId":"beea141f-1579-492a-b73d-78750998bc8d","week":"8","kpi_index":"15","value_num":"1","value_text":""},{"@odata.etag":"","ItemInternalId":"4ac7d21b-cb4a-41c9-a36e-2431ad37ced8","week":"8","kpi_index":"16","value_num":"40","value_text":""},{"@odata.etag":"","ItemInternalId":"e55de6b6-f593-4804-bb66-e8f21f48b50e","week":"8","kpi_index":"17","value_num":"8","value_text":""},{"@odata.etag":"","ItemInternalId":"7f707774-a377-4166-bf90-3a47b5106357","week":"8","kpi_index":"18","value_num":"28","value_text":""},{"@odata.etag":"","ItemInternalId":"6e9f40dc-0ea6-453a-a252-97823a0e6c01","week":"8","kpi_index":"19","value_num":"11","value_text":""},{"@odata.etag":"","ItemInternalId":"99212760-8078-44f3-a55a-a5953566d4e8","week":"8","kpi_index":"20","value_num":"","value_text":"Afghanistan x2, Angola x1, Dominican Republic x1, El Salvador x1, Ghanaian x1, Guinea-Bissau x1, Kenya x1, Mali x1, Somalia x1, Sudan x2, Sri Lanka x1, Saudi Arabia x1"},{"@odata.etag":"","ItemInternalId":"e2699d1c-f81c-4a9b-a610-2c920935c154","week":"8","kpi_index":"21","value_num":"","value_text":""},{"@odata.etag":"","ItemInternalId":"e51517ef-9253-4813-8caf-d44e3c8d6cfd","week":"8","kpi_index":"22","value_num":"0","value_text":""},{"@odata.etag":"","ItemInternalId":"d694326c-d434-4d87-ab2a-2691abbe2c1c","week":"8","kpi_index":"23","value_num":"0","value_text":""},{"@odata.etag":"","ItemInternalId":"14ef87b3-7ee7-4a50-ae1a-9ea08c27a4b3","week":"8","kpi_index":"24","value_num":"3","value_text":""},{"@odata.etag":"","ItemInternalId":"7b9d5cb5-42af-40b4-a0ea-807c617c6d77","week":"8","kpi_index":"25","value_num":"1620","value_text":""},{"@odata.etag":"","ItemInternalId":"1929e215-e815-4243-a5c6-3f41af4c4510","week":"8","kpi_index":"26","value_num":"1610","value_text":""},{"@odata.etag":"","ItemInternalId":"8cca8952-57d9-45a4-856b-dec0008562d3","week":"8","kpi_index":"27","value_num":"1595","value_text":""},{"@odata.etag":"","ItemInternalId":"01db0890-5000-47d1-a36c-df611277c6ba","week":"8","kpi_index":"28","value_num":"93","value_text":""},{"@odata.etag":"","ItemInternalId":"0cc9c29f-8b60-4249-b89c-583f6fddfaf1","week":"8","kpi_index":"29","value_num":"","value_text":"PPE shortage flagged Wed shift — resolved next day with additional stock delivery."},{"@odata.etag":"","ItemInternalId":"a92b5a5a-6df8-495b-a410-6ffc50ec307e","week":"9","kpi_index":"0","value_num":"96","value_text":""},{"@odata.etag":"","ItemInternalId":"6fefa6f1-7255-4fcc-89d4-6611d0b327b2","week":"9","kpi_index":"1","value_num":"7824","value_text":""},{"@odata.etag":"","ItemInternalId":"8d8d2fb0-85b9-450e-a693-a969a77e4391","week":"9","kpi_index":"3","value_num":"58","value_text":""},{"@odata.etag":"","ItemInternalId":"6148ed13-a705-4928-bb77-93f1868506fc","week":"9","kpi_index":"4","value_num":"38","value_text":""},{"@odata.etag":"","ItemInternalId":"0282c3a6-13a6-4f54-ac63-2807f3993aa6","week":"9","kpi_index":"5","value_num":"96","value_text":""},{"@odata.etag":"","ItemInternalId":"3d18b3ab-bf4a-4fb5-89b9-933e93a38df3","week":"9","kpi_index":"6","value_num":"0","value_text":""},{"@odata.etag":"","ItemInternalId":"94236930-111c-4a0e-9d94-409c81240e33","week":"9","kpi_index":"7","value_num":"31","value_text":""},{"@odata.etag":"","ItemInternalId":"7acbc8cd-2b9d-4357-9e11-f5be3e5249a8","week":"9","kpi_index":"8","value_num":"36","value_text":""},{"@odata.etag":"","ItemInternalId":"bc205905-cc9e-4173-a24e-12e45c3b42e8","week":"9","kpi_index":"9","value_num":"18","value_text":""},{"@odata.etag":"","ItemInternalId":"fba96094-3901-43af-9908-7e86b6e1e4e0","week":"9","kpi_index":"10","value_num":"6","value_text":""},{"@odata.etag":"","ItemInternalId":"71c8f1bf-9ccb-4f93-ad02-e6ba90b5fc3e","week":"9","kpi_index":"11","value_num":"5","value_text":""},{"@odata.etag":"","ItemInternalId":"b37b7e92-e8df-49a0-b679-4aa718e88db6","week":"9","kpi_index":"12","value_num":"1","value_text":""},{"@odata.etag":"","ItemInternalId":"b23315b9-76e3-40c7-9a3d-400bb71930c4","week":"9","kpi_index":"13","value_num":"1","value_text":""},{"@odata.etag":"","ItemInternalId":"b8a9cb8d-5eca-4b8d-b046-2226ff04e3fe","week":"9","kpi_index":"14","value_num":"5","value_text":""},{"@odata.etag":"","ItemInternalId":"8c04b3d3-192a-4aa0-a885-89d082335e26","week":"9","kpi_index":"15","value_num":"1","value_text":""},{"@odata.etag":"","ItemInternalId":"df5740de-7267-4872-92f0-793ee609bfff","week":"9","kpi_index":"16","value_num":"40","value_text":""},{"@odata.etag":"","ItemInternalId":"ac170e5e-6463-4a53-a3dd-a4d39dbfa997","week":"9","kpi_index":"17","value_num":"9","value_text":""},{"@odata.etag":"","ItemInternalId":"306dfc6e-d64c-41b6-ada2-1206a9d2ef98","week":"9","kpi_index":"18","value_num":"29","value_text":""},{"@odata.etag":"","ItemInternalId":"f0821ac4-463a-405b-a919-f6c762b3ff88","week":"9","kpi_index":"19","value_num":"10","value_text":""},{"@odata.etag":"","ItemInternalId":"99e78aff-7958-4e34-ab83-d024908bcd95","week":"9","kpi_index":"20","value_num":"","value_text":"Afghanistan x2, Angola x1, Dominican Republic x1, El Salvador x1, Ghanaian x1, Guinea-Bissau x1, Kenya x1, Mali x1, Somalia x1, Sudan x2, Sri Lanka x1, Saudi Arabia x1"},{"@odata.etag":"","ItemInternalId":"90b6e9db-d3dc-473b-9d06-a064d6b5a6c7","week":"9","kpi_index":"21","value_num":"","value_text":""},{"@odata.etag":"","ItemInternalId":"ef31e9a7-8bdd-4d9c-81c7-eabc15d3bd00","week":"9","kpi_index":"22","value_num":"0","value_text":""},{"@odata.etag":"","ItemInternalId":"d9252ef5-e3b7-481a-aaeb-c360ebbef6df","week":"9","kpi_index":"23","value_num":"0","value_text":""},{"@odata.etag":"","ItemInternalId":"6270fa3d-740d-405c-9ac5-e964ba718a63","week":"9","kpi_index":"24","value_num":"5","value_text":""}]}